FPGA1/src/compare.sv
`timescale 1ns / 1ps
`default_nettype none

module compare (
                input wire clk_in,
                input wire rst_in,
                input wire [10:0] x_com_in, // from COM module
                input wire [9:0]  y_com_in, // from COM module
                input wire com_valid_in,
                input wire [10:0] hcount, // from filter
                input wire [9:0]  vcount, // from filter 
                input wire [5:0] y_pixel, // from rgb_to_ycrcb
                input wire [1:0] color_select, // from switches, routed in toplevel
                input wire write_erase_select, // from switches, routed in toplevel
                input wire [7:0] pixel_from_bram, // current pixel at that spot in BRAM
                //output logic [16:0] pixel_addr_bram_check,
                output logic [7:0] pixel_for_bram, // pixel to write into the BRAM
                output logic [16:0] pixel_addr_forbram, // either the pixel that we want to check or the pixel that we want to store (depends on valid signal)
                output logic valid_pixel_forbram,
                //output logic [7:0] pixel_out_forvga,
                output logic pixelread_forvga_valid, // tells vga to read output of BRAM request because it is ready
                output logic pixeladdr_forvga_valid // tells vga to send address to read
            );

    //state params (outer FSM)
    localparam RESTING = 2'b00;
    localparam COM_RECEIVED = 2'b01;
    localparam COMPARING = 2'b10;

    //state params (inner FSM)
    localparam CALCULATE = 3'b000;
    localparam CHECK = 3'b001;
    localparam WAIT1 = 3'b010;
    localparam RECEIVE = 3'b011;
    localparam STORE = 3'b100;
    localparam WAIT2 = 3'b101;
    localparam VGAREAD = 3'b110;
    localparam WAIT3 = 3'b111;

    //color params
    localparam YELLOW = 8'b11000000; // 11 is MSBs indicates that it is written on
    localparam PINK = 8'b11000001;
    localparam GREEN = 8'b11000010;
    localparam RED = 8'b11000011;
    
    logic [1:0] outer_state;
    logic [2:0] inner_state;

    logic [10:0] x_com_current;
    logic [9:0] y_com_current;
    logic [16:0] com_address;
    logic [8:0][16:0] com_addresses_around;
    logic com_received_flag;
    logic address_in_com_flag;

    logic [10:0] curr_hcount;
    logic [9:0] curr_vcount;
    logic [7:0] pixel_yvalue;

    always_ff @(posedge clk_in) begin
        if (rst_in) begin
            inner_state <= CALCULATE;
            valid_pixel_forbram <= 0;
            curr_hcount <= 0;
            curr_vcount <= 0;
            pixel_yvalue <= 0;
            // resets com_addresses to the top left corner since no COM has been received yet
            com_addresses_around[0] <= 0;
            com_addresses_around[1] <= 0;
            com_addresses_around[2] <= 0;
            com_addresses_around[3] <= 0;
            com_addresses_around[4] <= 0;
            com_addresses_around[5] <= 0;
            com_addresses_around[6] <= 0;
            com_addresses_around[7] <= 0;
            com_addresses_around[8] <= 0;
        end
        else begin
            if (com_valid_in) begin // new COM received, need to calculate with the new one instead -- not sure about this?
                com_received_flag <= 1;
                x_com_current <= x_com_in;
                y_com_current <= y_com_in;
                com_address <= (y_com_in)*320 + x_com_in;
            end
            if (com_received_flag) begin // find the 9 pixels around the COM
                com_received_flag <= 0;
                if (x_com_in > 0 && x_com_in < 319) begin
                    if (y_com_in > 0 && y_com_in < 239) begin
                        com_addresses_around[0] <= com_address - 321;
                        com_addresses_around[1] <= com_address - 320;
                        com_addresses_around[2] <= com_address - 319;
                        com_addresses_around[3] <= com_address - 1;
                        com_addresses_around[4] <= com_address;
                        com_addresses_around[5] <= com_address + 1;
                        com_addresses_around[6] <= com_address + 319;
                        com_addresses_around[7] <= com_address + 320;
                        com_addresses_around[8] <= com_address + 321;
                    end
                    else if (y_com_in == 0) begin
                        com_addresses_around[0] <= 17'h12C01; // pixel outside frame
                        com_addresses_around[1] <= 17'h12C01;
                        com_addresses_around[2] <= 17'h12C01;
                        com_addresses_around[3] <= com_address - 1;
                        com_addresses_around[4] <= com_address;
                        com_addresses_around[5] <= com_address + 1;
                        com_addresses_around[6] <= com_address + 319;
                        com_addresses_around[7] <= com_address + 320;
                        com_addresses_around[8] <= com_address + 321;
                    end
                    else if (y_com_in == 239) begin
                        com_addresses_around[0] <= com_address - 321;
                        com_addresses_around[1] <= com_address - 320;
                        com_addresses_around[2] <= com_address - 319;
                        com_addresses_around[3] <= com_address - 1;
                        com_addresses_around[4] <= com_address;
                        com_addresses_around[5] <= com_address + 1;
                        com_addresses_around[6] <= 17'h12C01;
                        com_addresses_around[7] <= 17'h12C01;
                        com_addresses_around[8] <= 17'h12C01;
                    end
                end else if (x_com_in == 319) begin // this means we are in the rightmost line
                    if (y_com_in > 0 && y_com_in < 239) begin
                        com_addresses_around[0] <= com_address - 321;
                        com_addresses_around[1] <= com_address - 320;
                        com_addresses_around[2] <= 17'h12C01;
                        com_addresses_around[3] <= com_address - 1;
                        com_addresses_around[4] <= com_address;
                        com_addresses_around[5] <= 17'h12C01;
                        com_addresses_around[6] <= com_address + 319;
                        com_addresses_around[7] <= com_address + 320;
                        com_addresses_around[8] <= 17'h12C01;
                    end
                    else if (y_com_in == 0) begin
                        com_addresses_around[0] <= 17'h12C01; // pixel outside frame
                        com_addresses_around[1] <= 17'h12C01;
                        com_addresses_around[2] <= 17'h12C01;
                        com_addresses_around[3] <= com_address - 1;
                        com_addresses_around[4] <= com_address;
                        com_addresses_around[5] <= 17'h12C01;
                        com_addresses_around[6] <= com_address + 319;
                        com_addresses_around[7] <= com_address + 320;
                        com_addresses_around[8] <= 17'h12C01;
                    end
                    else if (y_com_in == 239) begin
                        com_addresses_around[0] <= com_address - 321;
                        com_addresses_around[1] <= com_address - 320;
                        com_addresses_around[2] <= 17'h12C01;
                        com_addresses_around[3] <= com_address - 1;
                        com_addresses_around[4] <= com_address;
                        com_addresses_around[5] <= 17'h12C01;
                        com_addresses_around[6] <= 17'h12C01;
                        com_addresses_around[7] <= 17'h12C01;
                        com_addresses_around[8] <= 17'h12C01;
                    end
                end else if (x_com_in == 0) begin // this means we are in the leftmost line
                    if (y_com_in > 0 && y_com_in < 239) begin
                        com_addresses_around[0] <= 17'h12C01;
                        com_addresses_around[1] <= com_address - 320;
                        com_addresses_around[2] <= com_address - 319;
                        com_addresses_around[3] <= 17'h12C01;
                        com_addresses_around[4] <= com_address;
                        com_addresses_around[5] <= com_address + 1;
                        com_addresses_around[6] <= 17'h12C01;
                        com_addresses_around[7] <= com_address + 320;
                        com_addresses_around[8] <= com_address + 321;
                    end
                    else if (y_com_in == 0) begin
                        com_addresses_around[0] <= 17'h12C01; // pixel outside frame
                        com_addresses_around[1] <= 17'h12C01;
                        com_addresses_around[2] <= 17'h12C01;
                        com_addresses_around[3] <= 17'h12C01;
                        com_addresses_around[4] <= com_address;
                        com_addresses_around[5] <= com_address + 1;
                        com_addresses_around[6] <= 17'h12C01;
                        com_addresses_around[7] <= com_address + 320;
                        com_addresses_around[8] <= com_address + 321;
                    end
                    else if (y_com_in == 239) begin
                        com_addresses_around[0] <= 17'h12C01;
                        com_addresses_around[1] <= com_address - 320;
                        com_addresses_around[2] <= com_address - 319;
                        com_addresses_around[3] <= 17'h12C01;
                        com_addresses_around[4] <= com_address;
                        com_addresses_around[5] <= com_address + 1;
                        com_addresses_around[6] <= 17'h12C01;
                        com_addresses_around[7] <= 17'h12C01;
                        com_addresses_around[8] <= 17'h12C01;
                    end
                end
            end
            case(inner_state) 
                CALCULATE: begin
                    
                    // calculate address
                    
                    if (curr_hcount != hcount || curr_vcount != vcount) begin // this means that we have received a new pixel 
                        inner_state <= CHECK;
                        pixel_yvalue <= {2'b00, y_pixel}; // save the pixel throughout a full loop
                        curr_hcount <= hcount;
                        curr_vcount <= vcount;
                        pixel_addr_forbram <= (vcount)*320 + hcount;
                    end
                    
                    // read pixel for VGA -- this will happen in top level and be synced to this FSM
                    pixelread_forvga_valid <= 0;
                end
                CHECK: begin
                    inner_state <= WAIT1;
                    if (pixel_addr_forbram == com_addresses_around[0] || pixel_addr_forbram == com_addresses_around[1] || pixel_addr_forbram == com_addresses_around[2] || pixel_addr_forbram == com_addresses_around[3] || pixel_addr_forbram == com_addresses_around[4] || pixel_addr_forbram == com_addresses_around[5] || pixel_addr_forbram == com_addresses_around[6] || pixel_addr_forbram == com_addresses_around[7] || pixel_addr_forbram == com_addresses_around[8]) begin
                        address_in_com_flag <= 1;
                    end else begin
                        address_in_com_flag <= 0;
                    end
                end
                WAIT1: begin
                    inner_state <= RECEIVE;
                end
                RECEIVE: begin
                    inner_state <= STORE;
                    if (write_erase_select == 0) begin // write mode
                        if (pixel_from_bram[7:6] == 2'b11) begin // colored pixel - don't write over it!
                            valid_pixel_forbram <= 0; 
                            pixel_for_bram <= pixel_from_bram;
                        end
                        else begin
                            valid_pixel_forbram <= 1;
                            if (address_in_com_flag) begin // write colored pixel
                                case (color_select)
                                    2'b00: begin
                                        pixel_for_bram <= YELLOW;
                                    end
                                    2'b01: begin
                                        pixel_for_bram <= PINK;
                                    end
                                    2'b10: begin
                                        pixel_for_bram <= GREEN;
                                    end
                                    2'b11: begin
                                        pixel_for_bram <= RED;
                                    end
                                endcase
                            end
                            else begin // write regular pixel
                                pixel_for_bram <= pixel_yvalue;
                            end
                        end
                    end else begin // erase mode
                        if (pixel_from_bram[7:6] == 2'b11) begin // colored pixel, either erase it or leave it
                            if (address_in_com_flag) begin // erase it
                                valid_pixel_forbram <= 1;
                                pixel_for_bram <= pixel_yvalue;
                            end
                            else begin // leave it
                                valid_pixel_forbram <= 0;
                                pixel_for_bram <= pixel_from_bram;
                            end
                        end
                        else begin // write regular pixel
                            valid_pixel_forbram <= 1;
                            pixel_for_bram <= pixel_yvalue;
                        end
                    end
                end
                STORE: begin
                    // pixel for BRAM is written in this state
                    inner_state <= WAIT2;
                    valid_pixel_forbram <= 0;
                end
                WAIT2: begin
                    inner_state <= VGAREAD;
                    pixeladdr_forvga_valid <= 1;
                end
                VGAREAD: begin
                    inner_state <= WAIT3;
                    pixeladdr_forvga_valid <= 0;
                end
                WAIT3: begin
                    inner_state <= CALCULATE;
                    pixelread_forvga_valid <= 1; // tells vga module to read the pixel for the VGA
                end
            endcase        
        end
    end

endmodule

`default_nettype wire

FPGA1/sim/compare_tb.sv
`timescale 1ns / 1ps
`default_nettype none

module compare_tb;

    //make logics for inputs and outputs!
    logic clk_in;
    logic rst_in;
    logic [10:0] x_com_in;
    logic [9:0] y_com_in;
    logic com_valid_in;
    logic [10:0] hcount_in;
    logic [9:0] vcount_in;
    logic [5:0] y_in;
    logic [1:0] color_sel;
    logic write_erase_sel;
    logic [7:0] bram_pixel_in;
    logic [7:0] bram_pixel_out;
    logic [16:0] bram_pixel_addr;
    logic bram_pixelwrite_valid;
    logic vga_pixelread_valid;
    logic vga_pixeladdr_valid;

    compare uut(.clk_in(clk_in), 
                .rst_in(rst_in),
                .x_com_in(x_com_in),
                .y_com_in(y_com_in),
                .com_valid_in(com_valid_in),
                .hcount(hcount_in),
                .vcount(vcount_in),
                .y_pixel(y_in),
                .color_select(color_sel),
                .write_erase_select(write_erase_sel),
                .pixel_from_bram(bram_pixel_in),
                .pixel_for_bram(bram_pixel_out),
                .pixel_addr_forbram(bram_pixel_addr),
                .valid_pixel_forbram(bram_pixelwrite_valid),
                .pixelread_forvga_valid(vga_pixelread_valid),
                .pixeladdr_forvga_valid(vga_pixeladdr_valid)
    );

    always begin
        #5;  //every 5 ns switch...so period of clock is 10 ns...100 MHz clock
        clk_in = !clk_in;
    end

    //initial block...this is our test simulation
    initial begin
        $dumpfile("compare.vcd"); //file to store value change dump (vcd)
        $dumpvars(0,compare_tb); //store everything at the current level and below
        $display("Starting Sim"); //print nice message
        clk_in = 0; //initialize clk (super important)
        rst_in = 0; //initialize rst (super important)
        x_com_in = 11'b0;
        y_com_in = 10'b0;
        com_valid_in = 0;
        hcount_in = 0;
        vcount_in = 0;
        y_in = 0;
        color_sel = 2'b01; // pink
        write_erase_sel = 0; // write mode

        #10  //wait a little bit of time at beginning
        rst_in = 1; //reset system
        #10; //hold high for a few clock cycles
        rst_in = 0;
        #5;
        // $display("Test 1: 9 clock cycles - write mode in pink");
        // for (int i = 0; i<9; i= i+1)begin
        //     if (i == 0) begin // send in valid COM
        //         x_com_in = 150;
        //         y_com_in = 100;
        //         com_valid_in = 1;
        //     end else if (i == 1) begin
        //         hcount_in = 100;
        //         vcount_in = 100;
        //         y_in = 6'b010101;
        //     end else if (i == 4) begin
        //         bram_pixel_in = 8'b00111111; // pixel not written on
        //     end

        //     $display("Cycle %4d values: ", i);
        //     $display("pixel from bram", bram_pixel_in);
        //     $display("pixel for bram", bram_pixel_out);
        //     $display("pixel addr for bram", bram_pixel_addr);
        //     $display("write to bram", bram_pixelwrite_valid);
        //     $display("read pixel vga signal", vga_pixelread_valid);
        //     $display("send address to bram for vga pixel signal", vga_pixeladdr_valid);
        //     $display("______");
        //     #10;
        // end
        
        // $display("Test 2: 17 clock cycles - write mode in pink");
        // for (int i = 0; i<17; i= i+1)begin
        //     if (i == 0) begin // send in valid COM
        //         x_com_in = 150;
        //         y_com_in = 100;
        //         com_valid_in = 1;
        //     end else if (i == 1) begin
        //         hcount_in = 100;
        //         vcount_in = 100;
        //         y_in = 6'b010101;
        //     end else if (i == 4) begin
        //         bram_pixel_in = 8'b00111111; // pixel not written on
        //     end else if (i == 9) begin
        //         hcount_in = 101;
        //         vcount_in = 100;
        //         y_in = 6'b010111;
        //     end else if (i == 12) begin
        //         bram_pixel_in = 8'b00100000; // pixel not written on
        //     end

        //     $display("Cycle %4d values: ", i);
        //     $display("pixel from bram", bram_pixel_in);
        //     $display("pixel for bram", bram_pixel_out);
        //     $display("pixel addr for bram", bram_pixel_addr);
        //     $display("write to bram", bram_pixelwrite_valid);
        //     $display("read pixel vga signal", vga_pixelread_valid);
        //     $display("send address to bram for vga pixel signal", vga_pixeladdr_valid);
        //     $display("______");
        //     #10;
        // end

        $display("Test 3: 17 clock cycles - write mode in pink, second pixel in COM");
        for (int i = 0; i<17; i= i+1)begin
            if (i == 0) begin // send in valid COM
                x_com_in = 150;
                y_com_in = 100;
                com_valid_in = 1;
            end else if (i == 1) begin
                hcount_in = 100;
                vcount_in = 100;
                y_in = 6'b010101;
            end else if (i == 4) begin
                bram_pixel_in = 8'b00111111; // pixel not written on
            end else if (i == 9) begin
                hcount_in = 151;
                vcount_in = 100;
                y_in = 6'b010111;
            end else if (i == 12) begin
                bram_pixel_in = 8'b00100000; // pixel not written on
            end

            $display("Cycle %4d values: ", i);
            $display("pixel from bram", bram_pixel_in);
            $display("pixel for bram", bram_pixel_out);
            $display("pixel addr for bram", bram_pixel_addr);
            $display("write to bram", bram_pixelwrite_valid);
            $display("read pixel vga signal", vga_pixelread_valid);
            $display("send address to bram for vga pixel signal", vga_pixeladdr_valid);
            $display("______");
            #10;
        end

        $display("Finishing Sim"); //print nice message
        $finish;


    end
endmodule //counter_tb

`default_nettype wire

FPGA1/compare.vcd
$date
	Sun Dec  4 14:32:07 2022
$end
$version
	Icarus Verilog
$end
$timescale
	1ps
$end
$scope module compare_tb $end
$var wire 1 ! vga_pixelread_valid $end
$var wire 1 " vga_pixeladdr_valid $end
$var wire 1 # bram_pixelwrite_valid $end
$var wire 8 $ bram_pixel_out [7:0] $end
$var wire 17 % bram_pixel_addr [16:0] $end
$var reg 8 & bram_pixel_in [7:0] $end
$var reg 1 ' clk_in $end
$var reg 2 ( color_sel [1:0] $end
$var reg 1 ) com_valid_in $end
$var reg 11 * hcount_in [10:0] $end
$var reg 1 + rst_in $end
$var reg 10 , vcount_in [9:0] $end
$var reg 1 - write_erase_sel $end
$var reg 11 . x_com_in [10:0] $end
$var reg 10 / y_com_in [9:0] $end
$var reg 6 0 y_in [5:0] $end
$scope module uut $end
$var wire 1 ' clk_in $end
$var wire 2 1 color_select [1:0] $end
$var wire 1 ) com_valid_in $end
$var wire 11 2 hcount [10:0] $end
$var wire 8 3 pixel_from_bram [7:0] $end
$var wire 1 + rst_in $end
$var wire 10 4 vcount [9:0] $end
$var wire 1 - write_erase_select $end
$var wire 11 5 x_com_in [10:0] $end
$var wire 10 6 y_com_in [9:0] $end
$var wire 6 7 y_pixel [5:0] $end
$var reg 1 8 address_in_com_flag $end
$var reg 17 9 com_address [16:0] $end
$var reg 153 : com_addresses_around [152:0] $end
$var reg 1 ; com_received_flag $end
$var reg 11 < curr_hcount [10:0] $end
$var reg 10 = curr_vcount [9:0] $end
$var reg 3 > inner_state [2:0] $end
$var reg 17 ? pixel_addr_forbram [16:0] $end
$var reg 8 @ pixel_for_bram [7:0] $end
$var reg 8 A pixel_yvalue [7:0] $end
$var reg 1 " pixeladdr_forvga_valid $end
$var reg 1 ! pixelread_forvga_valid $end
$var reg 1 # valid_pixel_forbram $end
$var reg 11 B x_com_current [10:0] $end
$var reg 10 C y_com_current [9:0] $end
$upscope $end
$scope begin $ivl_for_loop0 $end
$var integer 32 D i [31:0] $end
$upscope $end
$upscope $end
$enddefinitions $end
#0
$dumpvars
b0 D
bx C
bx B
bx A
bx @
bx ?
bx >
bx =
bx <
x;
bx :
bx 9
x8
b0 7
b0 6
b0 5
b0 4
bx 3
b0 2
b1 1
b0 0
b0 /
b0 .
0-
b0 ,
0+
b0 *
0)
b1 (
0'
bx &
bx %
bx $
x#
x"
x!
$end
#5000
1'
#10000
0'
1+
#15000
b0 :
b0 A
b0 =
b0 <
0#
b0 >
1'
#20000
0'
0+
#25000
0!
b111110110010110 9
b1100100 C
b10010110 B
1;
1'
1)
b1100100 /
b1100100 6
b10010110 .
b10010110 5
#30000
0'
#35000
b111110101100100 %
b111110101100100 ?
b1100100 =
b1100100 <
b10101 A
b1 >
b1111110110101110011111101101011000111111011010101001111101100101110011111011001011000111110110010101001111100010101110011111000101011000111110001010101 :
0;
1'
b10101 0
b10101 7
b1100100 ,
b1100100 4
b1100100 *
b1100100 2
b1 D
#40000
0'
#45000
08
b10 >
1;
1'
b10 D
#50000
0'
#55000
b11 >
0;
1'
b11 D
#60000
0'
#65000
b10101 $
b10101 @
1#
b100 >
1;
1'
b111111 &
b111111 3
b100 D
#70000
0'
#75000
0#
b101 >
0;
1'
b101 D
#80000
0'
#85000
1"
b110 >
1;
1'
b110 D
#90000
0'
#95000
0"
b111 >
0;
1'
b111 D
#100000
0'
#105000
1!
b0 >
1;
1'
b1000 D
#110000
0'
#115000
0!
b111110110010111 %
b111110110010111 ?
b10010111 <
b10111 A
b1 >
0;
1'
b10111 0
b10111 7
b10010111 *
b10010111 2
b1001 D
#120000
0'
#125000
18
b10 >
1;
1'
b1010 D
#130000
0'
#135000
b11 >
0;
1'
b1011 D
#140000
0'
#145000
b11000001 $
b11000001 @
1#
b100 >
1;
1'
b100000 &
b100000 3
b1100 D
#150000
0'
#155000
0#
b101 >
0;
1'
b1101 D
#160000
0'
#165000
1"
b110 >
1;
1'
b1110 D
#170000
0'
#175000
0"
b111 >
0;
1'
b1111 D
#180000
0'
#185000
1!
b0 >
1;
1'
b10000 D
#190000
0'
#195000
0!
0;
1'
b10001 D
